avk_django_datadog-0.1.0.8.dist-info/DESCRIPTION.rst
avk_django_datadog-0.1.0.8.dist-info/METADATA
avk_django_datadog-0.1.0.8.dist-info/RECORD
avk_django_datadog-0.1.0.8.dist-info/WHEEL
avk_django_datadog-0.1.0.8.dist-info/metadata.json
avk_django_datadog-0.1.0.8.dist-info/top_level.txt
datadog/__init__.py
datadog/middleware/__init__.py
datadog/middleware/request_handler.py
