Metadata-Version: 2.0
Name: avk-django-datadog
Version: 0.1.0.8
Summary: Simple Django middleware for submitting timings and exceptions to Datadog.
Home-page: https://github.com/conorbranagan/django-datadog
Author: Conor Branagan
Author-email: conor.branagan@gmail.com
License: BSD
Platform: UNKNOWN
